<?xml version="1.0" encoding="utf-8"?>
<Students>
  <Student student_id="1">
    <Name>Ana Bratucu</Name>
    <Education>
      <FormStudy education_id="0">
        <Name>Politehnica</Name>
        <City>Bucuresti</City>
        <Year>2020</Year>
        <Subjects>
          <Subject>
            <Name>Semantic Web</Name>
            <FinalGrade>10</FinalGrade>
            <Keyword>xml; dtd</Keyword>
            <Year>4</Year>
            <SubjectType>technologic</SubjectType>
          </Subject>
          <Subject>
            <Name>Computer Architecture</Name>
            <FinalGrade>8</FinalGrade>
            <Keyword>logic gates</Keyword>
            <Year>1</Year>
            <SubjectType>technologic</SubjectType>
          </Subject>
          <Subject>
            <Name>Educatie fizica</Name>
            <FinalGrade>10</FinalGrade>
            <Keyword>basketball</Keyword>
            <Year>1</Year>
            <SubjectType>arts</SubjectType>
          </Subject>
        </Subjects>
      </FormStudy>
      <FormStudy education_id="1">
        <Name>Colegiul National Ion Luca Caragiale</Name>
        <City>Bucuresti</City>
        <Year>2016</Year>
        <Subjects>
          <Subject>
            <Name>Matematica</Name>
            <FinalGrade>9</FinalGrade>
            <Keyword>integrale</Keyword>
            <Year>1,2,3,4</Year>
            <SubjectType>scientific</SubjectType>
          </Subject>
          <Subject>
            <Name>Romana</Name>
            <FinalGrade>9</FinalGrade>
            <Keyword>opere literare</Keyword>
            <Year>1,2,3,4</Year>
            <SubjectType>languages</SubjectType>
          </Subject>
          <Subject>
            <Name>Informatica</Name>
            <FinalGrade>10</FinalGrade>
            <Keyword>C++</Keyword>
            <Year>1,2,3,4</Year>
            <SubjectType>technologic</SubjectType>
          </Subject>
        </Subjects>
      </FormStudy>
    </Education>
    <InformalEducation>
      <Course>
        <Name>Web design</Name>
        <YearGraduation>2017</YearGraduation>
      </Course>
      <Course>
        <Name>Dezvoltare personala</Name>
        <YearGraduation>2018</YearGraduation>
      </Course>
    </InformalEducation>
  </Student>
</Students>
